[{"setName":"151","setCode":"sv3pt5","gameType":"POKEMON","cardCount":207},{"setName":"Ancient Origins","setCode":"xy7","gameType":"POKEMON","cardCount":101},{"setName":"Aquapolis","setCode":"ecard2","gameType":"POKEMON","cardCount":182},{"setName":"Arceus","setCode":"pl4","gameType":"POKEMON","cardCount":111},{"setName":"Ascended Heroes","setCode":"me2pt5","gameType":"POKEMON","cardCount":295},{"setName":"Astral Radiance","setCode":"swsh10","gameType":"POKEMON","cardCount":216},{"setName":"Astral Radiance Trainer Gallery","setCode":"swsh10tg","gameType":"POKEMON","cardCount":30},{"setName":"Base","setCode":"base1","gameType":"POKEMON","cardCount":102},{"setName":"Base Set 2","setCode":"base4","gameType":"POKEMON","cardCount":130},{"setName":"Battle Styles","setCode":"swsh5","gameType":"POKEMON","cardCount":183},{"setName":"Best of Game","setCode":"bp","gameType":"POKEMON","cardCount":9},{"setName":"Black & White","setCode":"bw1","gameType":"POKEMON","cardCount":115},{"setName":"Black Bolt","setCode":"zsv10pt5","gameType":"POKEMON","cardCount":172},{"setName":"Boundaries Crossed","setCode":"bw7","gameType":"POKEMON","cardCount":153},{"setName":"BREAKpoint","setCode":"xy9","gameType":"POKEMON","cardCount":126},{"setName":"BREAKthrough","setCode":"xy8","gameType":"POKEMON","cardCount":165},{"setName":"Brilliant Stars","setCode":"swsh9","gameType":"POKEMON","cardCount":186},{"setName":"Brilliant Stars Trainer Gallery","setCode":"swsh9tg","gameType":"POKEMON","cardCount":30},{"setName":"Burning Shadows","setCode":"sm3","gameType":"POKEMON","cardCount":177},{"setName":"BW Black Star Promos","setCode":"bwp","gameType":"POKEMON","cardCount":101},{"setName":"Call of Legends","setCode":"col1","gameType":"POKEMON","cardCount":106},{"setName":"Celebrations","setCode":"cel25","gameType":"POKEMON","cardCount":25},{"setName":"Celebrations: Classic Collection","setCode":"cel25c","gameType":"POKEMON","cardCount":25},{"setName":"Celestial Storm","setCode":"sm7","gameType":"POKEMON","cardCount":187},{"setName":"Champion's Path","setCode":"swsh35","gameType":"POKEMON","cardCount":80},{"setName":"Chilling Reign","setCode":"swsh6","gameType":"POKEMON","cardCount":233},{"setName":"Cosmic Eclipse","setCode":"sm12","gameType":"POKEMON","cardCount":272},{"setName":"Crimson Invasion","setCode":"sm4","gameType":"POKEMON","cardCount":126},{"setName":"Crown Zenith","setCode":"swsh12pt5","gameType":"POKEMON","cardCount":160},{"setName":"Crown Zenith Galarian Gallery","setCode":"swsh12pt5gg","gameType":"POKEMON","cardCount":70},{"setName":"Crystal Guardians","setCode":"ex14","gameType":"POKEMON","cardCount":100},{"setName":"Dark Explorers","setCode":"bw5","gameType":"POKEMON","cardCount":111},{"setName":"Darkness Ablaze","setCode":"swsh3","gameType":"POKEMON","cardCount":201},{"setName":"Delta Species","setCode":"ex11","gameType":"POKEMON","cardCount":114},{"setName":"Deoxys","setCode":"ex8","gameType":"POKEMON","cardCount":108},{"setName":"Destined Rivals","setCode":"sv10","gameType":"POKEMON","cardCount":244},{"setName":"Detective Pikachu","setCode":"det1","gameType":"POKEMON","cardCount":18},{"setName":"Diamond & Pearl","setCode":"dp1","gameType":"POKEMON","cardCount":130},{"setName":"Double Crisis","setCode":"dc1","gameType":"POKEMON","cardCount":34},{"setName":"DP Black Star Promos","setCode":"dpp","gameType":"POKEMON","cardCount":56},{"setName":"Dragon","setCode":"ex3","gameType":"POKEMON","cardCount":100},{"setName":"Dragon Frontiers","setCode":"ex15","gameType":"POKEMON","cardCount":101},{"setName":"Dragon Majesty","setCode":"sm75","gameType":"POKEMON","cardCount":80},{"setName":"Dragon Vault","setCode":"dv1","gameType":"POKEMON","cardCount":21},{"setName":"Dragons Exalted","setCode":"bw6","gameType":"POKEMON","cardCount":128},{"setName":"Emerald","setCode":"ex9","gameType":"POKEMON","cardCount":107},{"setName":"Emerging Powers","setCode":"bw2","gameType":"POKEMON","cardCount":98},{"setName":"Evolutions","setCode":"xy12","gameType":"POKEMON","cardCount":113},{"setName":"Evolving Skies","setCode":"swsh7","gameType":"POKEMON","cardCount":237},{"setName":"EX Trainer Kit 2 Minun","setCode":"tk2b","gameType":"POKEMON","cardCount":12},{"setName":"EX Trainer Kit 2 Plusle","setCode":"tk2a","gameType":"POKEMON","cardCount":12},{"setName":"EX Trainer Kit Latias","setCode":"tk1a","gameType":"POKEMON","cardCount":10},{"setName":"EX Trainer Kit Latios","setCode":"tk1b","gameType":"POKEMON","cardCount":10},{"setName":"Expedition Base Set","setCode":"ecard1","gameType":"POKEMON","cardCount":165},{"setName":"Fates Collide","setCode":"xy10","gameType":"POKEMON","cardCount":129},{"setName":"FireRed & LeafGreen","setCode":"ex6","gameType":"POKEMON","cardCount":116},{"setName":"Flashfire","setCode":"xy2","gameType":"POKEMON","cardCount":110},{"setName":"Forbidden Light","setCode":"sm6","gameType":"POKEMON","cardCount":150},{"setName":"Fossil","setCode":"base3","gameType":"POKEMON","cardCount":62},{"setName":"Furious Fists","setCode":"xy3","gameType":"POKEMON","cardCount":114},{"setName":"Fusion Strike","setCode":"swsh8","gameType":"POKEMON","cardCount":284},{"setName":"Generations","setCode":"g1","gameType":"POKEMON","cardCount":117},{"setName":"Great Encounters","setCode":"dp4","gameType":"POKEMON","cardCount":106},{"setName":"Guardians Rising","setCode":"sm2","gameType":"POKEMON","cardCount":180},{"setName":"Gym Challenge","setCode":"gym2","gameType":"POKEMON","cardCount":132},{"setName":"Gym Heroes","setCode":"gym1","gameType":"POKEMON","cardCount":132},{"setName":"HeartGold & SoulSilver","setCode":"hgss1","gameType":"POKEMON","cardCount":124},{"setName":"HGSS Black Star Promos","setCode":"hsp","gameType":"POKEMON","cardCount":25},{"setName":"Hidden Fates","setCode":"sm115","gameType":"POKEMON","cardCount":69},{"setName":"Hidden Fates Shiny Vault","setCode":"sma","gameType":"POKEMON","cardCount":94},{"setName":"Hidden Legends","setCode":"ex5","gameType":"POKEMON","cardCount":102},{"setName":"Holon Phantoms","setCode":"ex13","gameType":"POKEMON","cardCount":111},{"setName":"HS—Triumphant","setCode":"hgss4","gameType":"POKEMON","cardCount":103},{"setName":"HS—Undaunted","setCode":"hgss3","gameType":"POKEMON","cardCount":91},{"setName":"HS—Unleashed","setCode":"hgss2","gameType":"POKEMON","cardCount":96},{"setName":"Journey Together","setCode":"sv9","gameType":"POKEMON","cardCount":190},{"setName":"Jungle","setCode":"base2","gameType":"POKEMON","cardCount":64},{"setName":"Kalos Starter Set","setCode":"xy0","gameType":"POKEMON","cardCount":39},{"setName":"Legend Maker","setCode":"ex12","gameType":"POKEMON","cardCount":93},{"setName":"Legendary Collection","setCode":"base6","gameType":"POKEMON","cardCount":110},{"setName":"Legendary Treasures","setCode":"bw11","gameType":"POKEMON","cardCount":140},{"setName":"Legends Awakened","setCode":"dp6","gameType":"POKEMON","cardCount":146},{"setName":"Lost Origin","setCode":"swsh11","gameType":"POKEMON","cardCount":217},{"setName":"Lost Origin Trainer Gallery","setCode":"swsh11tg","gameType":"POKEMON","cardCount":30},{"setName":"Lost Thunder","setCode":"sm8","gameType":"POKEMON","cardCount":240},{"setName":"Majestic Dawn","setCode":"dp5","gameType":"POKEMON","cardCount":100},{"setName":"McDonald's Collection 2011","setCode":"mcd11","gameType":"POKEMON","cardCount":12},{"setName":"McDonald's Collection 2012","setCode":"mcd12","gameType":"POKEMON","cardCount":12},{"setName":"McDonald's Collection 2014","setCode":"mcd14","gameType":"POKEMON","cardCount":12},{"setName":"McDonald's Collection 2015","setCode":"mcd15","gameType":"POKEMON","cardCount":12},{"setName":"McDonald's Collection 2016","setCode":"mcd16","gameType":"POKEMON","cardCount":12},{"setName":"McDonald's Collection 2017","setCode":"mcd17","gameType":"POKEMON","cardCount":12},{"setName":"McDonald's Collection 2018","setCode":"mcd18","gameType":"POKEMON","cardCount":12},{"setName":"McDonald's Collection 2019","setCode":"mcd19","gameType":"POKEMON","cardCount":12},{"setName":"McDonald's Collection 2021","setCode":"mcd21","gameType":"POKEMON","cardCount":25},{"setName":"McDonald's Collection 2022","setCode":"mcd22","gameType":"POKEMON","cardCount":15},{"setName":"Mega Evolution","setCode":"me1","gameType":"POKEMON","cardCount":188},{"setName":"Mysterious Treasures","setCode":"dp2","gameType":"POKEMON","cardCount":124},{"setName":"Neo Destiny","setCode":"neo4","gameType":"POKEMON","cardCount":113},{"setName":"Neo Discovery","setCode":"neo2","gameType":"POKEMON","cardCount":75},{"setName":"Neo Genesis","setCode":"neo1","gameType":"POKEMON","cardCount":111},{"setName":"Neo Revelation","setCode":"neo3","gameType":"POKEMON","cardCount":66},{"setName":"Next Destinies","setCode":"bw4","gameType":"POKEMON","cardCount":103},{"setName":"Nintendo Black Star Promos","setCode":"np","gameType":"POKEMON","cardCount":40},{"setName":"Noble Victories","setCode":"bw3","gameType":"POKEMON","cardCount":102},{"setName":"Obsidian Flames","setCode":"sv3","gameType":"POKEMON","cardCount":230},{"setName":"Paldea Evolved","setCode":"sv2","gameType":"POKEMON","cardCount":279},{"setName":"Paldean Fates","setCode":"sv4pt5","gameType":"POKEMON","cardCount":245},{"setName":"Paradox Rift","setCode":"sv4","gameType":"POKEMON","cardCount":266},{"setName":"Phantasmal Flames","setCode":"me2","gameType":"POKEMON","cardCount":130},{"setName":"Phantom Forces","setCode":"xy4","gameType":"POKEMON","cardCount":124},{"setName":"Plasma Blast","setCode":"bw10","gameType":"POKEMON","cardCount":105},{"setName":"Plasma Freeze","setCode":"bw9","gameType":"POKEMON","cardCount":122},{"setName":"Plasma Storm","setCode":"bw8","gameType":"POKEMON","cardCount":138},{"setName":"Platinum","setCode":"pl1","gameType":"POKEMON","cardCount":133},{"setName":"Pokémon Futsal Collection","setCode":"fut20","gameType":"POKEMON","cardCount":5},{"setName":"Pokémon GO","setCode":"pgo","gameType":"POKEMON","cardCount":88},{"setName":"Pokémon Rumble","setCode":"ru1","gameType":"POKEMON","cardCount":16},{"setName":"POP Series 1","setCode":"pop1","gameType":"POKEMON","cardCount":17},{"setName":"POP Series 2","setCode":"pop2","gameType":"POKEMON","cardCount":17},{"setName":"POP Series 3","setCode":"pop3","gameType":"POKEMON","cardCount":17},{"setName":"POP Series 4","setCode":"pop4","gameType":"POKEMON","cardCount":17},{"setName":"POP Series 5","setCode":"pop5","gameType":"POKEMON","cardCount":17},{"setName":"POP Series 6","setCode":"pop6","gameType":"POKEMON","cardCount":17},{"setName":"POP Series 7","setCode":"pop7","gameType":"POKEMON","cardCount":17},{"setName":"POP Series 8","setCode":"pop8","gameType":"POKEMON","cardCount":17},{"setName":"POP Series 9","setCode":"pop9","gameType":"POKEMON","cardCount":17},{"setName":"Power Keepers","setCode":"ex16","gameType":"POKEMON","cardCount":108},{"setName":"Primal Clash","setCode":"xy5","gameType":"POKEMON","cardCount":164},{"setName":"Prismatic Evolutions","setCode":"sv8pt5","gameType":"POKEMON","cardCount":180},{"setName":"Rebel Clash","setCode":"swsh2","gameType":"POKEMON","cardCount":209},{"setName":"Rising Rivals","setCode":"pl2","gameType":"POKEMON","cardCount":120},{"setName":"Roaring Skies","setCode":"xy6","gameType":"POKEMON","cardCount":112},{"setName":"Ruby & Sapphire","setCode":"ex1","gameType":"POKEMON","cardCount":109},{"setName":"Sandstorm","setCode":"ex2","gameType":"POKEMON","cardCount":100},{"setName":"Scarlet & Violet","setCode":"sv1","gameType":"POKEMON","cardCount":258},{"setName":"Scarlet & Violet Black Star Promos","setCode":"svp","gameType":"POKEMON","cardCount":165},{"setName":"Scarlet & Violet Energies","setCode":"sve","gameType":"POKEMON","cardCount":16},{"setName":"Secret Wonders","setCode":"dp3","gameType":"POKEMON","cardCount":132},{"setName":"Shining Fates","setCode":"swsh45","gameType":"POKEMON","cardCount":73},{"setName":"Shining Fates Shiny Vault","setCode":"swsh45sv","gameType":"POKEMON","cardCount":122},{"setName":"Shining Legends","setCode":"sm35","gameType":"POKEMON","cardCount":81},{"setName":"Shrouded Fable","setCode":"sv6pt5","gameType":"POKEMON","cardCount":99},{"setName":"Silver Tempest","setCode":"swsh12","gameType":"POKEMON","cardCount":215},{"setName":"Silver Tempest Trainer Gallery","setCode":"swsh12tg","gameType":"POKEMON","cardCount":30},{"setName":"Skyridge","setCode":"ecard3","gameType":"POKEMON","cardCount":182},{"setName":"SM Black Star Promos","setCode":"smp","gameType":"POKEMON","cardCount":251},{"setName":"Southern Islands","setCode":"si1","gameType":"POKEMON","cardCount":18},{"setName":"Steam Siege","setCode":"xy11","gameType":"POKEMON","cardCount":116},{"setName":"Stellar Crown","setCode":"sv7","gameType":"POKEMON","cardCount":175},{"setName":"Stormfront","setCode":"dp7","gameType":"POKEMON","cardCount":106},{"setName":"Sun & Moon","setCode":"sm1","gameType":"POKEMON","cardCount":173},{"setName":"Supreme Victors","setCode":"pl3","gameType":"POKEMON","cardCount":153},{"setName":"Surging Sparks","setCode":"sv8","gameType":"POKEMON","cardCount":252},{"setName":"Sword & Shield","setCode":"swsh1","gameType":"POKEMON","cardCount":216},{"setName":"SWSH Black Star Promos","setCode":"swshp","gameType":"POKEMON","cardCount":304},{"setName":"Team Magma vs Team Aqua","setCode":"ex4","gameType":"POKEMON","cardCount":97},{"setName":"Team Rocket","setCode":"base5","gameType":"POKEMON","cardCount":83},{"setName":"Team Rocket Returns","setCode":"ex7","gameType":"POKEMON","cardCount":111},{"setName":"Team Up","setCode":"sm9","gameType":"POKEMON","cardCount":198},{"setName":"Temporal Forces","setCode":"sv5","gameType":"POKEMON","cardCount":218},{"setName":"Twilight Masquerade","setCode":"sv6","gameType":"POKEMON","cardCount":226},{"setName":"Ultra Prism","setCode":"sm5","gameType":"POKEMON","cardCount":178},{"setName":"Unbroken Bonds","setCode":"sm10","gameType":"POKEMON","cardCount":238},{"setName":"Unified Minds","setCode":"sm11","gameType":"POKEMON","cardCount":261},{"setName":"Unseen Forces","setCode":"ex10","gameType":"POKEMON","cardCount":145},{"setName":"Vivid Voltage","setCode":"swsh4","gameType":"POKEMON","cardCount":203},{"setName":"White Flare","setCode":"rsv10pt5","gameType":"POKEMON","cardCount":173},{"setName":"Wizards Black Star Promos","setCode":"basep","gameType":"POKEMON","cardCount":53},{"setName":"XY","setCode":"xy1","gameType":"POKEMON","cardCount":146},{"setName":"XY Black Star Promos","setCode":"xyp","gameType":"POKEMON","cardCount":216}]